[{"name":"[CF] WorldUnited.gg Mirror","url":"http://cdn.worldunited.gg/gamefiles/packed/","date_added":"2020-03-31T19:06:26.523"},{"name":"[CF] DavidCarbon Mirror","url":"http://g-sbrw.davidcarbon.download/","date_added":"2020-03-31T17:46:28"},{"name":"[CN] Zesty Mirror","url":"http://180.97.28.12:8765/ea_nfsw_section/","date_added":"2020-03-31T17:46:28"},{"name":"[FR] NightRiderz Mirror","url":"http://mirror.nightriderz.world/","date_added":"2020-03-31T17:46:28"},{"name":"[US] DavidCarbon Mirror - Alternative","url":"http://g2-sbrw.davidcarbon.download/","date_added":"2020-03-31T17:46:28"}]
